package_tea_hanyan/__init__.py
package_tea_hanyan/main.py
package_tea_hanyan-1.0.4.dist-info/METADATA
package_tea_hanyan-1.0.4.dist-info/WHEEL
package_tea_hanyan-1.0.4.dist-info/top_level.txt
package_tea_hanyan-1.0.4.dist-info/RECORD
