Metadata-Version: 2.1
Name: package-tea-hanyan
Version: 1.0.4
Summary: example for demo1
Home-page: https://github.com/hanyan007/package_tea_hanyan.git
Author: hanyan_news
Author-email: hanyan0572@gmail.com
License: BSD License
Project-URL: Source, https://github.com/hanyan007/package_tea_hanyan.git
Platform: all
Classifier: Intended Audience :: Developers
Classifier: Operating System :: OS Independent
Classifier: Natural Language :: Chinese (Simplified)
Classifier: Programming Language :: Python
Classifier: Programming Language :: Python :: 2
Classifier: Programming Language :: Python :: 2.7
Classifier: Programming Language :: Python :: 3
Classifier: Programming Language :: Python :: 3.5
Classifier: Programming Language :: Python :: 3.6
Classifier: Programming Language :: Python :: 3.7
Classifier: Programming Language :: Python :: 3.8
Classifier: Topic :: Software Development :: Libraries
Requires-Dist: restful-dnspod-log (==1.0.1)
Requires-Dist: dnspod-domain-log (==1.0.4)
